{"id": "35754007", "header": "Lamborghini Aventador SVJ bản 'Mây Sao Thổ', giới hạn chỉ 10 chiếc", "datetime": "2020-07-21T08:01:00.000+07:00", "summary": "Lấy cảm hứng từ những đám mây lục giác ngoài vũ trụ, Lamborghini Aventador SVJ Xago Edition được sản xuất giới hạn chỉ 10 chiếc trên toàn thế giới.", "content": "Ảnh: Carscoops ", "topic": "Xe cộ", "tag": ["Lamborghini Aventador SVJ", "Sao thổ", "Lục giác", "Ad Personam", "Lamborghini", "Đám mây", "HEXAGON", "Giới hạn", "Cá nhân hóa", "Agata Bolognese", "Vũ trụ", "Cảm hứng", "Hình lục giác", "Đảm trách", "Phiên bản", "Siêu xe", "Cực bắc", "Nhiệm", "Italia", "Xanh dương"], "link": "https://zingnews.vn/lamborghini-aventador-svj-ban-may-sao-tho-gioi-han-chi-10-chiec-post1109300.html"}