{"id": "35856948", "header": "Mazda lên kế hoạch sản xuất một loạt crossover mới", "datetime": "2020-07-30T06:24:28.000+07:00", "summary": "Mazda CX-5 thế hệ hiện tại mới được bán từ năm 2017 nhưng Mazda đã lên kế hoạch thay thế cho chiếc crossover bán chạy nhất của mình.", "content": "Theo đó, Mazda đã nộp nhãn hiệu cho tên \"CX-50\" với Văn phòng Bằng sáng chế châu Âu, đây có thể là tên mới của Mazda CX-5 thế hệ thứ ba sau khi ra mắt CX-30 gần đây.Mazda cũng đã đăng ký tên thương hiệu cho CX-10 cho đến CX-90, nhưng điều này có thể là để ngăn các nhà sản xuất ô tô khác sử dụng những tên này.Trong khi đó cũng xuất hiện thông tin về việc Mazda đang phát triển nền tảng RWD mới với động cơ 6 xy-lanh thẳng hàng cho Mazda 6 hoặc Mazda CX-50. Nền tảng này sẽ hỗ trợ các động cơ SkyActiv mới.Mazda CX-50 cũng có thể được trang bị động cơ SkyActiv-X 3.0L 6 xy-lanh thẳng hàng với hệ thống mild-hybrid 48 volt và động cơ SkyActiv-D 3.3L 6 xy-lanh thẳng hàng.Các phiên bản khác bao gồm: động cơ Skyactiv-G 4 xi-lanh 2.5 lít với động cơ hybrid nhẹ 48 volt sản sinh 187 mã lực, động cơ SkyActiv-G tăng áp 2.5 lít bốn xi-lanh với công suất tối đa 226 mã lực và 2.2 lít diesel SkyActiv-D.Nhiều khả năng, Mazda CX-50 Mazda được thiết kế theo phong cách coupe, đường bao mái thấp hơn, đèn pha LED và cản trước mới.Mazda CX-50 dự kiến ra mắt vào năm 2021 hoặc đầu năm 2022. ", "topic": "Xe cộ", "tag": ["CX-50", "Mazda CX-5", "Mazda", "Crossover", "Mazda 6", "CX-30", "Lên kế hoạch", "SKYACTIV-X", "Bán chạy", "RWD", "Thế hệ thứ ba", "SKYACTIV", "Thẳng hàng", "Thế hệ", "Volt", "Nhãn hiệu", "SKYACTIV-G", "Thay thế", "Nhà sản xuất ô tô", "Sản xuất"], "link": "https://vtc.vn/mazda-len-ke-hoach-san-xuat-mot-loat-crossover-moi-ar560460.html"}