{"id": "35883318", "header": "Vẫn có đường ra", "datetime": "2020-08-01T07:04:00.000+07:00", "summary": "Diễn biến mới về dịch Covid-19 khiến ngành du lịch xứ mình như đang phải ê ẩm. Dù số địa phương công bố có bệnh nhân mắc bệnh vẫn ít nhưng các tour có điểm đến ở nhiều địa phương khác cũng bị du khách hủy. Có những công ty du lịch méo mặt luôn.", "content": "- Nếu phải hoàn trả tiền tour cho khách, doanh nghiệp cũng sẽ được hoàn tiền từ các nhà cung cấp dịch vụ ở địa phương, tại sao lại méo?- Theo thông lệ, khi đến gần ngày thực hiện tour, đa số doanh nghiệp du lịch phải chuyển 100% chi phí trên hợp đồng cho nhà cung cấp. Tiền chi ra thì nhanh nhưng thương lượng hoàn trả không phải dễ. Khách sạn, nhà xe địa phương có thể yêu cầu giữ lại khoản đã thanh toán với lý do cấn trừ gối đầu cho thời gian tới. Doanh nghiệp du lịch vừa hoàn trả tiền mua tour hủy cho khách, vừa không lấy lại được tiền đã chi, cũng dễ “tụt huyết áp”. - Vậy không lẽ cứ tình huống bất khả kháng xảy ra là doanh nghiệp du lịch thua toàn tập?- Cũng không đến nỗi vậy. Doanh nghiệp nào quản trị tốt, có nhiều khách hàng thân thiết thì sẽ thương thảo để khách vẫn giữ tour, chỉ lùi thời điểm. Rồi nếu có uy tín với các nhà cung cấp, chuyện tiền bạc giữa hai bên cũng được thu xếp ổn thỏa dần. - Rốt cuộc, doanh nghiệp nào có nền tảng vững, giữ được chữ tín thì vẫn có đường ra. ", "topic": "Nhà đất", "tag": ["Tour", "Hủy", "Du lịch", "Dịch", "Du khách", "Điểm đến", "Địa phương", "Diễn biến", "Ê ẩm", "Méo mặt", "Công ty du lịch", "Hoàn trả", "Gần ngày", "Mắc bệnh", "Méo", "Nhà cung cấp dịch vụ", "Bệnh nhân", "Nhà cung cấp", "Gối đầu", "Thông lệ"], "link": "http://sggp.org.vn/van-co-duong-ra-676676.html"}