{"id": "35941294", "header": "Đọ cấu hình Galaxy Note20, Note20 Ultra và Pixel 4, iPhone 11 Pro", "datetime": "2020-08-06T10:23:00.000+07:00", "summary": "Samsung vừa công bố bộ đôi Note20 và Note20 Ultra cùng hàng loạt sản phẩm khác. Những sản phẩm này có đọ được với các đối thủ mạnh nhất hiện nay?", "content": "Trong sự kiện diễn ra tối 5/8 (giờ Việt Nam), Samsungđã công bố 5 dòng sản phẩm mới, trong đó nổi bật nhất là bộ đôi Note 20, Note 20 Ultra. Cả hai đều được cải tiến từ phần cứng tới phần mềm và bút S Pen.Note20 Ultra là thiết bịcao cấp hơn, được xây dựng dựa trên S20 Ultra. Máy trang bị màn hình cong hai bên, kích cỡ 6.9 inch, tấm nền Dynamic AMOLED 2X, độ phân giải 1440p+, tần suất làm tươi 120Hz, mặt lưng kính. Trong khi đó, Note20 dùng màn hình phẳng 6.7 inch, mặt lưng nhựa. Note 20 Ultra cũng là smartphoneđầu tiên được sử dụng kính cường lực Gorilla Glass Victus, còn Note 20 vẫn dùng kính Gorilla Glass 5 cũ.Là flagship mới nhất của Samsung, Note 20 và Note 20 Ultra có cấu hình như thế nào so với các thiết bị tiền nhiệm và đối thủ mạnh nhất hiện nay?(Theo The Verge) ", "topic": "Công nghệ ", "tag": ["Note20 Ultra", "Note 20 Ultra", "Note 20", "Samsung", "Dynamic AMOLED 2X", "Galaxy Note20", "Cấu hình", "Bộ đôi", "Pixel 4", "IPhone 11 Pro", "Đọ", "S20 Ultra", "S Pen", "Gorilla Glass Victus"], "link": "https://vietnamnet.vn/vn/cong-nghe/san-pham/do-cau-hinh-galaxy-note20-note20-ultra-va-pixel-4-iphone-11-pro-663907.html"}