{"id": "35950576", "header": "Những mỹ nhân từng hẹn hò tài tử Lâm Canh Tân", "datetime": "2020-08-07T06:05:00.000+07:00", "summary": "Đường tình của Lâm Canh Tân xuất hiện nhiều người đẹp từ hot girl mạng cho đến những mỹ nhân nổi tiếng showbiz.", "content": " ", "topic": "Giải trí", "tag": ["Lâm Canh Tân", "Tài tử", "Hẹn hò", "Mỹ nhân", "Hot girl", "Kinh tâm", "SINA", "Màu hạt dẻ", "Showbiz", "Vũ Lạc", "Vương Tư Thông", "Người đẹp", "Địch Nhân Kiệt", "Long vương", "Ngoại truyện", "Tây Du Ký", "Hoa ngữ", "Vương Lệ Khôn", "Tử anh", "Săn ảnh"], "link": "https://zingnews.vn/nhung-my-nhan-tung-hen-ho-tai-tu-lam-canh-tan-post1115737.html"}